grog/__init__.py
grog/grog.py
grog-0.93.dist-info/AUTHORS
grog-0.93.dist-info/LICENSE
grog-0.93.dist-info/METADATA
grog-0.93.dist-info/WHEEL
grog-0.93.dist-info/entry_points.txt
grog-0.93.dist-info/top_level.txt
grog-0.93.dist-info/RECORD
