Metadata-Version: 2.1
Name: grog
Version: 0.93
Summary: GeneRic wOrkload Generator
Home-page: https://gitlab.irit.fr/sepia-pub/grog
Author: Georges Da Costa
Author-email: georges.da-costa@irit.fr
License: UNKNOWN
Platform: UNKNOWN
Classifier: Programming Language :: Python :: 3
Classifier: License :: OSI Approved :: GNU General Public License v3 or later (GPLv3+)
Classifier: Operating System :: OS Independent
Requires-Python: >=3.6
License-File: LICENSE
License-File: AUTHORS
